mentat_lss/__init__.py
mentat_lss/cosmo_utils.py
mentat_lss/dataset.py
mentat_lss/emulator.py
mentat_lss/gpsclass.py
mentat_lss/training_loops.py
mentat_lss/utils.py
mentat_lss/_vendor/__init__.py
mentat_lss/_vendor/fastpt/FASTPT.py
mentat_lss/_vendor/fastpt/FASTPT_original.py
mentat_lss/_vendor/fastpt/FASTPT_simple.py
mentat_lss/_vendor/fastpt/HT.py
mentat_lss/_vendor/fastpt/IA.py
mentat_lss/_vendor/fastpt/IA_ABD.py
mentat_lss/_vendor/fastpt/IA_ta.py
mentat_lss/_vendor/fastpt/IA_tt.py
mentat_lss/_vendor/fastpt/J_k.py
mentat_lss/_vendor/fastpt/J_table.py
mentat_lss/_vendor/fastpt/OV.py
mentat_lss/_vendor/fastpt/P_extend.py
mentat_lss/_vendor/fastpt/RG_RK4.py
mentat_lss/_vendor/fastpt/RG_RK4_filt.py
mentat_lss/_vendor/fastpt/RG_STS.py
mentat_lss/_vendor/fastpt/RG_ani.py
mentat_lss/_vendor/fastpt/RSD.py
mentat_lss/_vendor/fastpt/RSD_ItypeII.py
mentat_lss/_vendor/fastpt/Wigner_symbols.py
mentat_lss/_vendor/fastpt/__init__.py
mentat_lss/_vendor/fastpt/bias_choice_plot.py
mentat_lss/_vendor/fastpt/fastpt_extr.py
mentat_lss/_vendor/fastpt/filter_Pk.py
mentat_lss/_vendor/fastpt/gamma_funcs.py
mentat_lss/_vendor/fastpt/get_nu1_nu2.py
mentat_lss/_vendor/fastpt/info.py
mentat_lss/_vendor/fastpt/initialize_params.py
mentat_lss/_vendor/fastpt/kPol.py
mentat_lss/_vendor/fastpt/matter_power_spt.py
mentat_lss/_vendor/fastpt/matter_power_spt_updated_G3_factor.py
mentat_lss/_vendor/fastpt/param_matrix.py
mentat_lss/_vendor/symbolic_pofk/__init__.py
mentat_lss/_vendor/symbolic_pofk/linear.py
mentat_lss/models/analytic_terms.py
mentat_lss/models/blocks.py
mentat_lss/models/single_transformer.py
mentat_lss/models/stacked_mlp.py
mentat_lss/models/stacked_transformer.py
mentat_lss-0.9.5.dist-info/licenses/LICENSE
mentat_lss-0.9.5.dist-info/METADATA
mentat_lss-0.9.5.dist-info/WHEEL
mentat_lss-0.9.5.dist-info/top_level.txt
mentat_lss-0.9.5.dist-info/RECORD
