Metadata-Version: 2.4
Name: mentat-lss
Version: 0.9.5
Summary: package for emulating galaxy power spectrum multipoles using neural networks
Author-email: Joe Adamo <jadamo@arizona.edu>
License:                     GNU GENERAL PUBLIC LICENSE
Project-URL: Homepage, https://github.com/jadamo/mentat-lss
Requires-Python: >=3.9
License-File: LICENSE
Requires-Dist: setuptools
Requires-Dist: build
Requires-Dist: numpy<2
Requires-Dist: scipy
Requires-Dist: torch
Requires-Dist: pytest
Requires-Dist: tqdm
Requires-Dist: pyyaml
Requires-Dist: colossus
Dynamic: license-file
